helloworld/__init__.py
helloworld/helloworld.py
helloworld_jammer-0.0.2.dist-info/LICENSE
helloworld_jammer-0.0.2.dist-info/METADATA
helloworld_jammer-0.0.2.dist-info/WHEEL
helloworld_jammer-0.0.2.dist-info/top_level.txt
helloworld_jammer-0.0.2.dist-info/RECORD
