Metadata-Version: 2.1
Name: helloworld-jammer
Version: 0.0.2
Summary: Returns 'Hello, World!'
Home-page: https://github.com/jammer42/helloworld-package
License: UNKNOWN
Platform: UNKNOWN
Classifier: Programming Language :: Python :: 3
Classifier: Programming Language :: Python :: 3.9
Classifier: Operating System :: OS Independent
Classifier: License :: OSI Approved :: MIT License
Provides-Extra: dev
Requires-Dist: pytest ; extra == 'dev'
